play3d/__about__.py
play3d/__init__.py
play3d/matrix.py
play3d/models.py
play3d/three_d.py
play3d/utils.py
play3d-0.1.5.dist-info/LICENSE
play3d-0.1.5.dist-info/METADATA
play3d-0.1.5.dist-info/WHEEL
play3d-0.1.5.dist-info/top_level.txt
play3d-0.1.5.dist-info/RECORD
