Metadata-Version: 2.1
Name: play3d
Version: 0.1.5
Summary: Basic 3D world playground with animations and completely from scratch.
Home-page: https://github.com/timabilov/python-play3d
Author: timabilov
Author-email: timabilov33@gmail.com
License: MIT License
Keywords: python 3d play3d three_d projection mvp
Platform: UNKNOWN
Classifier: Development Status :: 1 - Planning
Classifier: Intended Audience :: Developers
Classifier: License :: OSI Approved :: MIT License
Classifier: Operating System :: OS Independent
Classifier: Topic :: Software Development
Classifier: Topic :: Education
Classifier: Topic :: Scientific/Engineering :: Visualization
Classifier: Programming Language :: Python
Classifier: Programming Language :: Python :: 3
Classifier: Programming Language :: Python :: 3.6
Classifier: Programming Language :: Python :: 3.7
Classifier: Programming Language :: Python :: 3.8
Classifier: Programming Language :: Python :: 3.9
Requires-Dist: numpy
